[{"label_no":1,"is_up_down":0,"line_name":"26路","station_name":"会展中心","lng":"113733388","lat":"34775294","carfare":"1.00","first_time":"06:00-21:00","dept_name":"四公司","yn_use_ic_a":"Y","yn_use_ic_b":"Y","yn_use_ic_c":"Y","yn_use_ic_d":"Y","alias":""},{"label_no":2,"is_up_down":0,"line_name":"26路","station_name":"商务内环路西八街站","lng":"113733251","lat":"34773449","carfare":"1.00","first_time":"06:00-21:00","dept_name":"四公司","yn_use_ic_a":"Y","yn_use_ic_b":"Y","yn_use_ic_c":"Y","yn_use_ic_d":"Y","alias":""},{"label_no":3,"is_up_down":0,"line_name":"26路","station_name":"市房管局","lng":"113738707","lat":"34775412","carfare":"1.00","first_time":"06:00-21:00","dept_name":"四公司","yn_use_ic_a":"Y","yn_use_ic_b":"Y","yn_use_ic_c":"Y","yn_use_ic_d":"Y","alias":""},{"label_no":4,"is_up_down":0,"line_name":"26路","station_name":"郑州市四十七中","lng":"113746107","lat":"34776591","carfare":"1.00","first_time":"06:00-21:00","dept_name":"四公司","yn_use_ic_a":"Y","yn_use_ic_b":"Y","yn_use_ic_c":"Y","yn_use_ic_d":"Y","alias":""},{"label_no":5,"is_up_down":0,"line_name":"26路","station_name":"市公交总公司","lng":"113750110","lat":"34774563","carfare":"1.00","first_time":"06:00-21:00","dept_name":"四公司","yn_use_ic_a":"Y","yn_use_ic_b":"Y","yn_use_ic_c":"Y","yn_use_ic_d":"Y","alias":""},{"label_no":6,"is_up_down":0,"line_name":"26路","station_name":"金水东路黄河南路","lng":"113749238","lat":"34768860","carfare":"1.00","first_time":"06:00-21:00","dept_name":"四公司","yn_use_ic_a":"Y","yn_use_ic_b":"Y","yn_use_ic_c":"Y","yn_use_ic_d":"Y","alias":""},{"label_no":7,"is_up_down":0,"line_name":"26路","station_name":"金水东路聚源路","lng":"113744431","lat":"34767550","carfare":"1.00","first_time":"06:00-21:00","dept_name":"四公司","yn_use_ic_a":"Y","yn_use_ic_b":"Y","yn_use_ic_c":"Y","yn_use_ic_d":"Y","alias":""},{"label_no":8,"is_up_down":0,"line_name":"26路","station_name":"金水东路通泰路","lng":"113739529","lat":"34767096","carfare":"1.00","first_time":"06:00-21:00","dept_name":"四公司","yn_use_ic_a":"Y","yn_use_ic_b":"Y","yn_use_ic_c":"Y","yn_use_ic_d":"Y","alias":""},{"label_no":9,"is_up_down":0,"line_name":"26路","station_name":"金水立交站","lng":"113724226","lat":"34768271","carfare":"1.00","first_time":"06:00-21:00","dept_name":"四公司","yn_use_ic_a":"Y","yn_use_ic_b":"Y","yn_use_ic_c":"Y","yn_use_ic_d":"Y","alias":""},{"label_no":10,"is_up_down":0,"line_name":"26路","station_name":"金水路民航路站","lng":"113719066","lat":"34768342","carfare":"1.00","first_time":"06:00-21:00","dept_name":"四公司","yn_use_ic_a":"Y","yn_use_ic_b":"Y","yn_use_ic_c":"Y","yn_use_ic_d":"Y","alias":""},{"label_no":11,"is_up_down":0,"line_name":"26路","station_name":"金水路未来路","lng":"113715445","lat":"34768655","carfare":"1.00","first_time":"06:00-21:00","dept_name":"四公司","yn_use_ic_a":"Y","yn_use_ic_b":"Y","yn_use_ic_c":"Y","yn_use_ic_d":"Y","alias":""},{"label_no":12,"is_up_down":0,"line_name":"26路","station_name":"金水路东明路站","lng":"113704934","lat":"34768956","carfare":"1.00","first_time":"06:00-21:00","dept_name":"四公司","yn_use_ic_a":"Y","yn_use_ic_b":"Y","yn_use_ic_c":"Y","yn_use_ic_d":"Y","alias":""},{"label_no":13,"is_up_down":0,"line_name":"26路","station_name":"国际饭店","lng":"113700229","lat":"34769233","carfare":"1.00","first_time":"06:00-21:00","dept_name":"四公司","yn_use_ic_a":"Y","yn_use_ic_b":"Y","yn_use_ic_c":"Y","yn_use_ic_d":"Y","alias":""},{"label_no":14,"is_up_down":0,"line_name":"26路","station_name":"紫荆山","lng":"113687615","lat":"34769101","carfare":"1.00","first_time":"06:00-21:00","dept_name":"四公司","yn_use_ic_a":"Y","yn_use_ic_b":"Y","yn_use_ic_c":"Y","yn_use_ic_d":"Y","alias":""},{"label_no":15,"is_up_down":0,"line_name":"26路","station_name":"工人新村","lng":"113681889","lat":"34764655","carfare":"1.00","first_time":"06:00-21:00","dept_name":"四公司","yn_use_ic_a":"Y","yn_use_ic_b":"Y","yn_use_ic_c":"Y","yn_use_ic_d":"Y","alias":""},{"label_no":16,"is_up_down":0,"line_name":"26路","station_name":"人民南路","lng":"113676001","lat":"34760395","carfare":"1.00","first_time":"06:00-21:00","dept_name":"四公司","yn_use_ic_a":"Y","yn_use_ic_b":"Y","yn_use_ic_c":"Y","yn_use_ic_d":"Y","alias":""},{"label_no":17,"is_up_down":0,"line_name":"26路","station_name":"火车站 (北出站口)","lng":"113668505","lat":"34754651","carfare":"1.00","first_time":"06:00-21:00","dept_name":"四公司","yn_use_ic_a":"Y","yn_use_ic_b":"Y","yn_use_ic_c":"Y","yn_use_ic_d":"Y","alias":""},{"label_no":1,"is_up_down":1,"line_name":"26路","station_name":"火车站 (北出站口)","lng":"113668505","lat":"34754655","carfare":"1.00","first_time":"06:00-21:00","dept_name":"四公司","yn_use_ic_a":"Y","yn_use_ic_b":"Y","yn_use_ic_c":"Y","yn_use_ic_d":"Y","alias":""},{"label_no":2,"is_up_down":1,"line_name":"26路","station_name":"人民南路","lng":"113674782","lat":"34759383","carfare":"1.00","first_time":"06:00-21:00","dept_name":"四公司","yn_use_ic_a":"Y","yn_use_ic_b":"Y","yn_use_ic_c":"Y","yn_use_ic_d":"Y","alias":""},{"label_no":3,"is_up_down":1,"line_name":"26路","station_name":"工人新村","lng":"113681698","lat":"34764509","carfare":"1.00","first_time":"06:00-21:00","dept_name":"四公司","yn_use_ic_a":"Y","yn_use_ic_b":"Y","yn_use_ic_c":"Y","yn_use_ic_d":"Y","alias":""},{"label_no":4,"is_up_down":1,"line_name":"26路","station_name":"紫荆山","lng":"113691124","lat":"34769167","carfare":"1.00","first_time":"06:00-21:00","dept_name":"四公司","yn_use_ic_a":"Y","yn_use_ic_b":"Y","yn_use_ic_c":"Y","yn_use_ic_d":"Y","alias":""},{"label_no":5,"is_up_down":1,"line_name":"26路","station_name":"国际饭店","lng":"113699756","lat":"34768973","carfare":"1.00","first_time":"06:00-21:00","dept_name":"四公司","yn_use_ic_a":"Y","yn_use_ic_b":"Y","yn_use_ic_c":"Y","yn_use_ic_d":"Y","alias":""},{"label_no":6,"is_up_down":1,"line_name":"26路","station_name":"金水路东明路站","lng":"113705362","lat":"34768753","carfare":"1.00","first_time":"06:00-21:00","dept_name":"四公司","yn_use_ic_a":"Y","yn_use_ic_b":"Y","yn_use_ic_c":"Y","yn_use_ic_d":"Y","alias":""},{"label_no":7,"is_up_down":1,"line_name":"26路","station_name":"金水路未来路","lng":"113713793","lat":"34768628","carfare":"1.00","first_time":"06:00-21:00","dept_name":"四公司","yn_use_ic_a":"Y","yn_use_ic_b":"Y","yn_use_ic_c":"Y","yn_use_ic_d":"Y","alias":""},{"label_no":8,"is_up_down":1,"line_name":"26路","station_name":"金水路民航路站","lng":"113719097","lat":"34768175","carfare":"1.00","first_time":"06:00-21:00","dept_name":"四公司","yn_use_ic_a":"Y","yn_use_ic_b":"Y","yn_use_ic_c":"Y","yn_use_ic_d":"Y","alias":""},{"label_no":9,"is_up_down":1,"line_name":"26路","station_name":"金水立交站","lng":"113724204","lat":"34767603","carfare":"1.00","first_time":"06:00-21:00","dept_name":"四公司","yn_use_ic_a":"Y","yn_use_ic_b":"Y","yn_use_ic_c":"Y","yn_use_ic_d":"Y","alias":""},{"label_no":10,"is_up_down":1,"line_name":"26路","station_name":"金水东路通泰路","lng":"113740060","lat":"34766621","carfare":"1.00","first_time":"06:00-21:00","dept_name":"四公司","yn_use_ic_a":"Y","yn_use_ic_b":"Y","yn_use_ic_c":"Y","yn_use_ic_d":"Y","alias":""},{"label_no":11,"is_up_down":1,"line_name":"26路","station_name":"金水东路聚源路","lng":"113744811","lat":"34767057","carfare":"1.00","first_time":"06:00-21:00","dept_name":"四公司","yn_use_ic_a":"Y","yn_use_ic_b":"Y","yn_use_ic_c":"Y","yn_use_ic_d":"Y","alias":""},{"label_no":12,"is_up_down":1,"line_name":"26路","station_name":"黄河南路金水东路","lng":"113751068","lat":"34770856","carfare":"1.00","first_time":"06:00-21:00","dept_name":"四公司","yn_use_ic_a":"Y","yn_use_ic_b":"Y","yn_use_ic_c":"Y","yn_use_ic_d":"Y","alias":""},{"label_no":13,"is_up_down":1,"line_name":"26路","station_name":"市公交总公司","lng":"113750832","lat":"34773459","carfare":"1.00","first_time":"06:00-21:00","dept_name":"四公司","yn_use_ic_a":"Y","yn_use_ic_b":"Y","yn_use_ic_c":"Y","yn_use_ic_d":"Y","alias":""},{"label_no":14,"is_up_down":1,"line_name":"26路","station_name":"郑州市四十七中","lng":"113746107","lat":"34776587","carfare":"1.00","first_time":"06:00-21:00","dept_name":"四公司","yn_use_ic_a":"Y","yn_use_ic_b":"Y","yn_use_ic_c":"Y","yn_use_ic_d":"Y","alias":""},{"label_no":15,"is_up_down":1,"line_name":"26路","station_name":"商务内环路商务东三街","lng":"113739587","lat":"34777091","carfare":"1.00","first_time":"06:00-21:00","dept_name":"四公司","yn_use_ic_a":"Y","yn_use_ic_b":"Y","yn_use_ic_c":"Y","yn_use_ic_d":"Y","alias":""},{"label_no":16,"is_up_down":1,"line_name":"26路","station_name":"商务内环路九如路站","lng":"113739314","lat":"34779970","carfare":"1.00","first_time":"06:00-21:00","dept_name":"四公司","yn_use_ic_a":"Y","yn_use_ic_b":"Y","yn_use_ic_c":"Y","yn_use_ic_d":"Y","alias":""},{"label_no":17,"is_up_down":1,"line_name":"26路","station_name":"商务内环路东一街","lng":"113736197","lat":"34782635","carfare":"1.00","first_time":"06:00-21:00","dept_name":"四公司","yn_use_ic_a":"Y","yn_use_ic_b":"Y","yn_use_ic_c":"Y","yn_use_ic_d":"Y","alias":""},{"label_no":18,"is_up_down":1,"line_name":"26路","station_name":"商务内环路众意路站","lng":"113730020","lat":"34782938","carfare":"1.00","first_time":"06:00-21:00","dept_name":"四公司","yn_use_ic_a":"Y","yn_use_ic_b":"Y","yn_use_ic_c":"Y","yn_use_ic_d":"Y","alias":""},{"label_no":19,"is_up_down":1,"line_name":"26路","station_name":"商务内环路众意西路","lng":"113728213","lat":"34782301","carfare":"1.00","first_time":"06:00-21:00","dept_name":"四公司","yn_use_ic_a":"Y","yn_use_ic_b":"Y","yn_use_ic_c":"Y","yn_use_ic_d":"Y","alias":""},{"label_no":20,"is_up_down":1,"line_name":"26路","station_name":"商务内环路西二街站","lng":"113726595","lat":"34778987","carfare":"1.00","first_time":"06:00-21:00","dept_name":"四公司","yn_use_ic_a":"Y","yn_use_ic_b":"Y","yn_use_ic_c":"Y","yn_use_ic_d":"Y","alias":""},{"label_no":21,"is_up_down":1,"line_name":"26路","station_name":"商务内环路西六街站","lng":"113728842","lat":"34775609","carfare":"1.00","first_time":"06:00-21:00","dept_name":"四公司","yn_use_ic_a":"Y","yn_use_ic_b":"Y","yn_use_ic_c":"Y","yn_use_ic_d":"Y","alias":""},{"label_no":22,"is_up_down":1,"line_name":"26路","station_name":"会展中心","lng":"113733388","lat":"34775294","carfare":"1.00","first_time":"06:00-21:00","dept_name":"四公司","yn_use_ic_a":"Y","yn_use_ic_b":"Y","yn_use_ic_c":"Y","yn_use_ic_d":"Y","alias":""}]